apart_concept/__init__.py
apart_concept-1.0.0.dist-info/LICENSE
apart_concept-1.0.0.dist-info/METADATA
apart_concept-1.0.0.dist-info/WHEEL
apart_concept-1.0.0.dist-info/top_level.txt
apart_concept-1.0.0.dist-info/zip-safe
apart_concept-1.0.0.dist-info/RECORD
